MANIFEST.in
README.md
requirements.txt
sendf.py
setup.cfg
setup.py
upnp.py
scripts/sendf
sendf.egg-info/PKG-INFO
sendf.egg-info/SOURCES.txt
sendf.egg-info/dependency_links.txt
sendf.egg-info/requires.txt
sendf.egg-info/top_level.txt