Metadata-Version: 1.0
Name: sendf
Version: 0.0.2
Summary: send files
Home-page: UNKNOWN
Author: Hui Peng Hu
Author-email: woohp135@gmail.com
License: UNKNOWN
Platform: UNKNOWN
